{"nodes": [{"id": "pkg_dev_stats_widget", "label": "dev-stats-widget", "file_type": "code", "type": "package", "ecosystem": "go", "source_file": "go.mod", "source_location": "L1"}], "edges": [{"source": "pkg_dev_stats_widget", "target": "pkg_github_com_docker_docker", "relation": "depends_on", "context": "dependency", "confidence": "EXTRACTED", "confidence_score": 1.0, "source_file": "go.mod", "source_location": "L1", "weight": 1.0}, {"source": "pkg_dev_stats_widget", "target": "pkg_github_com_wailsapp_wails_v2", "relation": "depends_on", "context": "dependency", "confidence": "EXTRACTED", "confidence_score": 1.0, "source_file": "go.mod", "source_location": "L1", "weight": 1.0}, {"source": "pkg_dev_stats_widget", "target": "pkg_golang_org_x_crypto", "relation": "depends_on", "context": "dependency", "confidence": "EXTRACTED", "confidence_score": 1.0, "source_file": "go.mod", "source_location": "L1", "weight": 1.0}, {"source": "pkg_dev_stats_widget", "target": "pkg_git_sr_ht_jackmordaunt_go_toast_v2", "relation": "depends_on", "context": "dependency", "confidence": "EXTRACTED", "confidence_score": 1.0, "source_file": "go.mod", "source_location": "L1", "weight": 1.0}, {"source": "pkg_dev_stats_widget", "target": "pkg_github_com_microsoft_go_winio", "relation": "depends_on", "context": "dependency", "confidence": "EXTRACTED", "confidence_score": 1.0, "source_file": "go.mod", "source_location": "L1", "weight": 1.0}, {"source": "pkg_dev_stats_widget", "target": "pkg_github_com_bep_debounce", "relation": "depends_on", "context": "dependency", "confidence": "EXTRACTED", "confidence_score": 1.0, "source_file": "go.mod", "source_location": "L1", "weight": 1.0}, {"source": "pkg_dev_stats_widget", "target": "pkg_github_com_cespare_xxhash_v2", "relation": "depends_on", "context": "dependency", "confidence": "EXTRACTED", "confidence_score": 1.0, "source_file": "go.mod", "source_location": "L1", "weight": 1.0}, {"source": "pkg_dev_stats_widget", "target": "pkg_github_com_containerd_errdefs", "relation": "depends_on", "context": "dependency", "confidence": "EXTRACTED", "confidence_score": 1.0, "source_file": "go.mod", "source_location": "L1", "weight": 1.0}, {"source": "pkg_dev_stats_widget", "target": "pkg_github_com_containerd_errdefs_pkg", "relation": "depends_on", "context": "dependency", "confidence": "EXTRACTED", "confidence_score": 1.0, "source_file": "go.mod", "source_location": "L1", "weight": 1.0}, {"source": "pkg_dev_stats_widget", "target": "pkg_github_com_containerd_log", "relation": "depends_on", "context": "dependency", "confidence": "EXTRACTED", "confidence_score": 1.0, "source_file": "go.mod", "source_location": "L1", "weight": 1.0}, {"source": "pkg_dev_stats_widget", "target": "pkg_github_com_distribution_reference", "relation": "depends_on", "context": "dependency", "confidence": "EXTRACTED", "confidence_score": 1.0, "source_file": "go.mod", "source_location": "L1", "weight": 1.0}, {"source": "pkg_dev_stats_widget", "target": "pkg_github_com_docker_go_connections", "relation": "depends_on", "context": "dependency", "confidence": "EXTRACTED", "confidence_score": 1.0, "source_file": "go.mod", "source_location": "L1", "weight": 1.0}, {"source": "pkg_dev_stats_widget", "target": "pkg_github_com_docker_go_units", "relation": "depends_on", "context": "dependency", "confidence": "EXTRACTED", "confidence_score": 1.0, "source_file": "go.mod", "source_location": "L1", "weight": 1.0}, {"source": "pkg_dev_stats_widget", "target": "pkg_github_com_felixge_httpsnoop", "relation": "depends_on", "context": "dependency", "confidence": "EXTRACTED", "confidence_score": 1.0, "source_file": "go.mod", "source_location": "L1", "weight": 1.0}, {"source": "pkg_dev_stats_widget", "target": "pkg_github_com_go_logr_logr", "relation": "depends_on", "context": "dependency", "confidence": "EXTRACTED", "confidence_score": 1.0, "source_file": "go.mod", "source_location": "L1", "weight": 1.0}, {"source": "pkg_dev_stats_widget", "target": "pkg_github_com_go_logr_stdr", "relation": "depends_on", "context": "dependency", "confidence": "EXTRACTED", "confidence_score": 1.0, "source_file": "go.mod", "source_location": "L1", "weight": 1.0}, {"source": "pkg_dev_stats_widget", "target": "pkg_github_com_go_ole_go_ole", "relation": "depends_on", "context": "dependency", "confidence": "EXTRACTED", "confidence_score": 1.0, "source_file": "go.mod", "source_location": "L1", "weight": 1.0}, {"source": "pkg_dev_stats_widget", "target": "pkg_github_com_godbus_dbus_v5", "relation": "depends_on", "context": "dependency", "confidence": "EXTRACTED", "confidence_score": 1.0, "source_file": "go.mod", "source_location": "L1", "weight": 1.0}, {"source": "pkg_dev_stats_widget", "target": "pkg_github_com_google_uuid", "relation": "depends_on", "context": "dependency", "confidence": "EXTRACTED", "confidence_score": 1.0, "source_file": "go.mod", "source_location": "L1", "weight": 1.0}, {"source": "pkg_dev_stats_widget", "target": "pkg_github_com_gorilla_websocket", "relation": "depends_on", "context": "dependency", "confidence": "EXTRACTED", "confidence_score": 1.0, "source_file": "go.mod", "source_location": "L1", "weight": 1.0}, {"source": "pkg_dev_stats_widget", "target": "pkg_github_com_jchv_go_winloader", "relation": "depends_on", "context": "dependency", "confidence": "EXTRACTED", "confidence_score": 1.0, "source_file": "go.mod", "source_location": "L1", "weight": 1.0}, {"source": "pkg_dev_stats_widget", "target": "pkg_github_com_labstack_echo_v4", "relation": "depends_on", "context": "dependency", "confidence": "EXTRACTED", "confidence_score": 1.0, "source_file": "go.mod", "source_location": "L1", "weight": 1.0}, {"source": "pkg_dev_stats_widget", "target": "pkg_github_com_labstack_gommon", "relation": "depends_on", "context": "dependency", "confidence": "EXTRACTED", "confidence_score": 1.0, "source_file": "go.mod", "source_location": "L1", "weight": 1.0}, {"source": "pkg_dev_stats_widget", "target": "pkg_github_com_leaanthony_go_ansi_parser", "relation": "depends_on", "context": "dependency", "confidence": "EXTRACTED", "confidence_score": 1.0, "source_file": "go.mod", "source_location": "L1", "weight": 1.0}, {"source": "pkg_dev_stats_widget", "target": "pkg_github_com_leaanthony_gosod", "relation": "depends_on", "context": "dependency", "confidence": "EXTRACTED", "confidence_score": 1.0, "source_file": "go.mod", "source_location": "L1", "weight": 1.0}, {"source": "pkg_dev_stats_widget", "target": "pkg_github_com_leaanthony_slicer", "relation": "depends_on", "context": "dependency", "confidence": "EXTRACTED", "confidence_score": 1.0, "source_file": "go.mod", "source_location": "L1", "weight": 1.0}, {"source": "pkg_dev_stats_widget", "target": "pkg_github_com_leaanthony_u", "relation": "depends_on", "context": "dependency", "confidence": "EXTRACTED", "confidence_score": 1.0, "source_file": "go.mod", "source_location": "L1", "weight": 1.0}, {"source": "pkg_dev_stats_widget", "target": "pkg_github_com_mattn_go_colorable", "relation": "depends_on", "context": "dependency", "confidence": "EXTRACTED", "confidence_score": 1.0, "source_file": "go.mod", "source_location": "L1", "weight": 1.0}, {"source": "pkg_dev_stats_widget", "target": "pkg_github_com_mattn_go_isatty", "relation": "depends_on", "context": "dependency", "confidence": "EXTRACTED", "confidence_score": 1.0, "source_file": "go.mod", "source_location": "L1", "weight": 1.0}, {"source": "pkg_dev_stats_widget", "target": "pkg_github_com_moby_docker_image_spec", "relation": "depends_on", "context": "dependency", "confidence": "EXTRACTED", "confidence_score": 1.0, "source_file": "go.mod", "source_location": "L1", "weight": 1.0}, {"source": "pkg_dev_stats_widget", "target": "pkg_github_com_moby_sys_atomicwriter", "relation": "depends_on", "context": "dependency", "confidence": "EXTRACTED", "confidence_score": 1.0, "source_file": "go.mod", "source_location": "L1", "weight": 1.0}, {"source": "pkg_dev_stats_widget", "target": "pkg_github_com_moby_term", "relation": "depends_on", "context": "dependency", "confidence": "EXTRACTED", "confidence_score": 1.0, "source_file": "go.mod", "source_location": "L1", "weight": 1.0}, {"source": "pkg_dev_stats_widget", "target": "pkg_github_com_morikuni_aec", "relation": "depends_on", "context": "dependency", "confidence": "EXTRACTED", "confidence_score": 1.0, "source_file": "go.mod", "source_location": "L1", "weight": 1.0}, {"source": "pkg_dev_stats_widget", "target": "pkg_github_com_opencontainers_go_digest", "relation": "depends_on", "context": "dependency", "confidence": "EXTRACTED", "confidence_score": 1.0, "source_file": "go.mod", "source_location": "L1", "weight": 1.0}, {"source": "pkg_dev_stats_widget", "target": "pkg_github_com_opencontainers_image_spec", "relation": "depends_on", "context": "dependency", "confidence": "EXTRACTED", "confidence_score": 1.0, "source_file": "go.mod", "source_location": "L1", "weight": 1.0}, {"source": "pkg_dev_stats_widget", "target": "pkg_github_com_pkg_browser", "relation": "depends_on", "context": "dependency", "confidence": "EXTRACTED", "confidence_score": 1.0, "source_file": "go.mod", "source_location": "L1", "weight": 1.0}, {"source": "pkg_dev_stats_widget", "target": "pkg_github_com_pkg_errors", "relation": "depends_on", "context": "dependency", "confidence": "EXTRACTED", "confidence_score": 1.0, "source_file": "go.mod", "source_location": "L1", "weight": 1.0}, {"source": "pkg_dev_stats_widget", "target": "pkg_github_com_rivo_uniseg", "relation": "depends_on", "context": "dependency", "confidence": "EXTRACTED", "confidence_score": 1.0, "source_file": "go.mod", "source_location": "L1", "weight": 1.0}, {"source": "pkg_dev_stats_widget", "target": "pkg_github_com_samber_lo", "relation": "depends_on", "context": "dependency", "confidence": "EXTRACTED", "confidence_score": 1.0, "source_file": "go.mod", "source_location": "L1", "weight": 1.0}, {"source": "pkg_dev_stats_widget", "target": "pkg_github_com_tkrajina_go_reflector", "relation": "depends_on", "context": "dependency", "confidence": "EXTRACTED", "confidence_score": 1.0, "source_file": "go.mod", "source_location": "L1", "weight": 1.0}, {"source": "pkg_dev_stats_widget", "target": "pkg_github_com_valyala_bytebufferpool", "relation": "depends_on", "context": "dependency", "confidence": "EXTRACTED", "confidence_score": 1.0, "source_file": "go.mod", "source_location": "L1", "weight": 1.0}, {"source": "pkg_dev_stats_widget", "target": "pkg_github_com_valyala_fasttemplate", "relation": "depends_on", "context": "dependency", "confidence": "EXTRACTED", "confidence_score": 1.0, "source_file": "go.mod", "source_location": "L1", "weight": 1.0}, {"source": "pkg_dev_stats_widget", "target": "pkg_github_com_wailsapp_go_webview2", "relation": "depends_on", "context": "dependency", "confidence": "EXTRACTED", "confidence_score": 1.0, "source_file": "go.mod", "source_location": "L1", "weight": 1.0}, {"source": "pkg_dev_stats_widget", "target": "pkg_github_com_wailsapp_mimetype", "relation": "depends_on", "context": "dependency", "confidence": "EXTRACTED", "confidence_score": 1.0, "source_file": "go.mod", "source_location": "L1", "weight": 1.0}, {"source": "pkg_dev_stats_widget", "target": "pkg_go_opentelemetry_io_auto_sdk", "relation": "depends_on", "context": "dependency", "confidence": "EXTRACTED", "confidence_score": 1.0, "source_file": "go.mod", "source_location": "L1", "weight": 1.0}, {"source": "pkg_dev_stats_widget", "target": "pkg_go_opentelemetry_io_contrib_instrumentation_net_http_otelhttp", "relation": "depends_on", "context": "dependency", "confidence": "EXTRACTED", "confidence_score": 1.0, "source_file": "go.mod", "source_location": "L1", "weight": 1.0}, {"source": "pkg_dev_stats_widget", "target": "pkg_go_opentelemetry_io_otel", "relation": "depends_on", "context": "dependency", "confidence": "EXTRACTED", "confidence_score": 1.0, "source_file": "go.mod", "source_location": "L1", "weight": 1.0}, {"source": "pkg_dev_stats_widget", "target": "pkg_go_opentelemetry_io_otel_exporters_otlp_otlptrace_otlptracehttp", "relation": "depends_on", "context": "dependency", "confidence": "EXTRACTED", "confidence_score": 1.0, "source_file": "go.mod", "source_location": "L1", "weight": 1.0}, {"source": "pkg_dev_stats_widget", "target": "pkg_go_opentelemetry_io_otel_metric", "relation": "depends_on", "context": "dependency", "confidence": "EXTRACTED", "confidence_score": 1.0, "source_file": "go.mod", "source_location": "L1", "weight": 1.0}, {"source": "pkg_dev_stats_widget", "target": "pkg_go_opentelemetry_io_otel_trace", "relation": "depends_on", "context": "dependency", "confidence": "EXTRACTED", "confidence_score": 1.0, "source_file": "go.mod", "source_location": "L1", "weight": 1.0}, {"source": "pkg_dev_stats_widget", "target": "pkg_golang_org_x_net", "relation": "depends_on", "context": "dependency", "confidence": "EXTRACTED", "confidence_score": 1.0, "source_file": "go.mod", "source_location": "L1", "weight": 1.0}, {"source": "pkg_dev_stats_widget", "target": "pkg_golang_org_x_sys", "relation": "depends_on", "context": "dependency", "confidence": "EXTRACTED", "confidence_score": 1.0, "source_file": "go.mod", "source_location": "L1", "weight": 1.0}, {"source": "pkg_dev_stats_widget", "target": "pkg_golang_org_x_text", "relation": "depends_on", "context": "dependency", "confidence": "EXTRACTED", "confidence_score": 1.0, "source_file": "go.mod", "source_location": "L1", "weight": 1.0}, {"source": "pkg_dev_stats_widget", "target": "pkg_gotest_tools_v3", "relation": "depends_on", "context": "dependency", "confidence": "EXTRACTED", "confidence_score": 1.0, "source_file": "go.mod", "source_location": "L1", "weight": 1.0}]}